ml_infrastructure/__init__.py
ml_infrastructure/app.py
ml_infrastructure/data_manager.py
ml_infrastructure/evaluator.py
ml_infrastructure/example.py
ml_infrastructure/manager.py
ml_infrastructure/model.py
ml_infrastructure/trainer.py
ml_infrastructure/static/js/jquery.min.js
ml_infrastructure/static/js/plotly-latest.min.js
ml_infrastructure/static/styles/bootstrap-theme.min.css
ml_infrastructure/static/styles/bootstrap.min.css
ml_infrastructure/templates/control.html
ml_infrastructure/templates/eval.html
ml_infrastructure/templates/header.html
ml_infrastructure/templates/index.html
ml_infrastructure/templates/loss.html
ml_infrastructure/templates/stopForm.html
ml_infrastructure/templates/trainingEval.html
ml_infrastructure/templates/trainingLoss.html
ml_infrastructure/templates/validationEval.html
ml_infrastructure/templates/validationLoss.html
ml_infrastructure-1.8.1.dist-info/LICENSE.rst
ml_infrastructure-1.8.1.dist-info/METADATA
ml_infrastructure-1.8.1.dist-info/WHEEL
ml_infrastructure-1.8.1.dist-info/top_level.txt
ml_infrastructure-1.8.1.dist-info/RECORD
