Metadata-Version: 2.1
Name: ml-infrastructure
Version: 1.8.1
Summary: Software infrastructure to for machine learning
Author: Ada L
Author-email: the.nostra.tymus@gmail.com
License: MIT
Keywords: machine learning
Classifier: Development Status :: 3 - Alpha
Classifier: Intended Audience :: Developers
Classifier: License :: OSI Approved :: MIT License
Classifier: Programming Language :: Python :: 3
License-File: LICENSE.rst
Requires-Dist: flask
Requires-Dist: turbo-flask
Requires-Dist: plotly
Requires-Dist: requests
Requires-Dist: torch
Requires-Dist: numpy
